[
  {
    "handle": "odontocompany",
    "followers": 208187,
    "posts": 1624,
    "overallScore": 79,
    "timestamp": "2026-01-16T17:52:42.041Z"
  },
  {
    "handle": "odontoalto",
    "followers": 2677,
    "posts": 304,
    "overallScore": 75,
    "timestamp": "2026-01-21T13:18:48.549Z"
  },
  {
    "handle": "odontomarcelamendes",
    "followers": 1931,
    "posts": 96,
    "overallScore": 55,
    "timestamp": "2026-01-16T17:59:43.467Z"
  },
  {
    "handle": "jotadentista",
    "followers": 6518,
    "posts": 544,
    "overallScore": 80,
    "timestamp": "2026-01-16T18:05:34.352Z"
  },
  {
    "handle": "drigoralmeida",
    "followers": 1,
    "posts": 0,
    "overallScore": 2,
    "timestamp": "2026-01-16T18:06:27.566Z"
  },
  {
    "handle": "digordealmeida",
    "followers": 17,
    "posts": 0,
    "overallScore": 5,
    "timestamp": "2026-01-16T18:07:22.654Z"
  },
  {
    "handle": "ferbaldassa",
    "followers": 9006,
    "posts": 589,
    "overallScore": 75,
    "timestamp": "2026-01-16T18:09:11.525Z"
  },
  {
    "handle": "dra.annabotelho",
    "followers": 1501,
    "posts": 29,
    "overallScore": 48,
    "timestamp": "2026-01-16T18:22:06.862Z"
  },
  {
    "handle": "dra.marcia.sampaio",
    "followers": 2231,
    "posts": 87,
    "overallScore": 71,
    "timestamp": "2026-01-16T18:23:34.328Z"
  },
  {
    "handle": "capim.br",
    "followers": 21046,
    "posts": 246,
    "overallScore": 78,
    "criteria": {
      "frequency": 75,
      "ctaAndLinks": 95,
      "positioningClarity": 98,
      "socialProof": 90
    },
    "timestamp": "2026-01-21T15:37:56.325Z"
  }
]